dimdrop/__init__.py
dimdrop/layers/__init__.py
dimdrop/layers/clustering_layer.py
dimdrop/losses/__init__.py
dimdrop/losses/tsne_loss.py
dimdrop/losses/vae_loss.py
dimdrop/models/__init__.py
dimdrop/models/autoencoder.py
dimdrop/models/dec.py
dimdrop/models/deepcluster.py
dimdrop/models/param_tsne.py
dimdrop/models/vasc.py
dimdrop/regularizers/__init__.py
dimdrop/regularizers/kmeans_reg.py
dimdrop/regularizers/tsne_reg.py
dimdrop/util/__init__.py
dimdrop/util/rbm.py
dimdrop/util/sequence.py
dimdrop/util/transform.py
dimdrop/util/tsne.py
dimdrop-0.1.0.dist-info/LICENSE
dimdrop-0.1.0.dist-info/METADATA
dimdrop-0.1.0.dist-info/WHEEL
dimdrop-0.1.0.dist-info/top_level.txt
dimdrop-0.1.0.dist-info/RECORD
