Metadata-Version: 2.1
Name: dimdrop
Version: 0.1.0
Summary: Providing some dimensionality reduction methods using Machine Learning
Home-page: https://github.com/theodedeken/dimdrop
Author: Theo Dedeken
Author-email: theo.dedeken@telenet.be
License: UNKNOWN
Platform: UNKNOWN
Classifier: Programming Language :: Python :: 3
Classifier: License :: OSI Approved :: MIT License
Classifier: Operating System :: OS Independent
Requires-Dist: numpy
Requires-Dist: keras
Requires-Dist: sklearn
